time_split/__init__.py
time_split/__main__.py
time_split/_backend/__init__.py
time_split/_backend/_datetime_index_like.py
time_split/_backend/_limits.py
time_split/_backend/_process_available.py
time_split/_backend/_schedule.py
time_split/_backend/_span.py
time_split/_backend/_splitter.py
time_split/_docstrings.py
time_split/_frontend/__init__.py
time_split/_frontend/_plot.py
time_split/_frontend/_progress.py
time_split/_frontend/_split.py
time_split/_frontend/_to_string.py
time_split/_frontend/_weight.py
time_split/_support.py
time_split/app/__init__.py
time_split/app/_create_explorer_link.py
time_split/app/reexport/__init__.py
time_split/cli.py
time_split/integration/__init__.py
time_split/integration/_log_progress.py
time_split/integration/base.py
time_split/integration/pandas/__init__.py
time_split/integration/pandas/_impl.py
time_split/integration/polars/__init__.py
time_split/integration/polars/_impl.py
time_split/integration/sklearn/__init__.py
time_split/integration/sklearn/_impl.py
time_split/py.typed
time_split/settings.py
time_split/support/__init__.py
time_split/support/types.py
time_split/types.py
time_split-1.2.0.dist-info/METADATA
time_split-1.2.0.dist-info/WHEEL
time_split-1.2.0.dist-info/entry_points.txt
time_split-1.2.0.dist-info/licenses/LICENSE.md
time_split-1.2.0.dist-info/RECORD
