Metadata-Version: 2.4
Name: time-split
Version: 1.2.0
Summary: Time-based k-fold validation splits for heterogeneous data.
License: MIT
License-File: LICENSE.md
Keywords: hyper,parameter,optimization,cross,validation,time,temporal,heterogenous,data
Author: Richard Sundqvist
Author-email: richard.sundqvist@live.se
Requires-Python: >=3.11
Classifier: Development Status :: 5 - Production/Stable
Classifier: Intended Audience :: Developers
Classifier: Intended Audience :: Science/Research
Classifier: Operating System :: POSIX :: Linux
Classifier: Operating System :: MacOS
Classifier: Operating System :: Microsoft :: Windows
Classifier: License :: OSI Approved :: MIT License
Classifier: Natural Language :: English
Classifier: Typing :: Typed
Classifier: Programming Language :: Python :: 3
Classifier: Programming Language :: Python :: 3 :: Only
Classifier: Programming Language :: Python :: 3.11
Classifier: Programming Language :: Python :: 3.12
Classifier: Programming Language :: Python :: 3.13
Classifier: Programming Language :: Python :: 3.14
Provides-Extra: app
Provides-Extra: plotting
Requires-Dist: click ; extra == "app"
Requires-Dist: matplotlib ; extra == "plotting"
Requires-Dist: pandas (>=2.0.3)
Requires-Dist: rics (>=6.0.1)
Requires-Dist: seaborn ; extra == "plotting"
Requires-Dist: time-split-app (>=1.1.0) ; extra == "app"
Project-URL: Bug Tracker, https://github.com/rsundqvist/time-split/issues
Project-URL: Changelog, https://github.com/rsundqvist/time-split/blob/master/CHANGELOG.md
Project-URL: Documentation, https://time-split
Project-URL: Homepage, https://github.com/rsundqvist/time-split
Project-URL: Repository, https://github.com/rsundqvist/time-split
